ForeTiS/__init__.py
ForeTiS/optim_pipeline.py
ForeTiS/run.py
ForeTiS/evaluation/__init__.py
ForeTiS/evaluation/eval_metrics.py
ForeTiS/model/__init__.py
ForeTiS/model/_base_model.py
ForeTiS/model/_baseline_model.py
ForeTiS/model/_model_classes.py
ForeTiS/model/_model_functions.py
ForeTiS/model/_sklearn_model.py
ForeTiS/model/_stat_model.py
ForeTiS/model/_template_sklearn_model.py
ForeTiS/model/_template_stat_model.py
ForeTiS/model/_template_tensorflow_model.py
ForeTiS/model/_template_torch_model.py
ForeTiS/model/_tensorflow_model.py
ForeTiS/model/_torch_model.py
ForeTiS/model/ard.py
ForeTiS/model/averagehistorical.py
ForeTiS/model/averagemoving.py
ForeTiS/model/averageseasonal.py
ForeTiS/model/averageseasonallag.py
ForeTiS/model/bayesridge.py
ForeTiS/model/elasticnet.py
ForeTiS/model/es.py
ForeTiS/model/evars-gpr.py
ForeTiS/model/gprtf.py
ForeTiS/model/lasso.py
ForeTiS/model/lstm.py
ForeTiS/model/lstmbayes.py
ForeTiS/model/mlp.py
ForeTiS/model/mlpbayes.py
ForeTiS/model/ridge.py
ForeTiS/model/sarima.py
ForeTiS/model/sarimax.py
ForeTiS/model/xgboost.py
ForeTiS/model/_additionalmodels/__init__.py
ForeTiS/model/_additionalmodels/gpr_sklearn.py
ForeTiS/model/_additionalmodels/lstmbayes_intel.py
ForeTiS/model/_additionalmodels/mlpbayes_intel.py
ForeTiS/optimization/__init__.py
ForeTiS/optimization/optuna_optim.py
ForeTiS/postprocess/__init__.py
ForeTiS/postprocess/model_reuse.py
ForeTiS/postprocess/results_analysis.py
ForeTiS/postprocess/run_interference.py
ForeTiS/preprocess/DateCalenderFeatures.py
ForeTiS/preprocess/FeatureAdder.py
ForeTiS/preprocess/StatisticalFeatures.py
ForeTiS/preprocess/__init__.py
ForeTiS/preprocess/base_dataset.py
ForeTiS/preprocess/raw_data_functions.py
ForeTiS/tutorial_data/__init__.py
ForeTiS/utils/__init__.py
ForeTiS/utils/check_functions.py
ForeTiS/utils/helper_functions.py
ForeTiS-0.0.6.dist-info/LICENSE
ForeTiS-0.0.6.dist-info/METADATA
ForeTiS-0.0.6.dist-info/WHEEL
ForeTiS-0.0.6.dist-info/top_level.txt
ForeTiS-0.0.6.dist-info/RECORD
